conrun/__init__.py
conrun/runner.py
conrun-0.1.3.dist-info/licenses/LICENSE
conrun-0.1.3.dist-info/METADATA
conrun-0.1.3.dist-info/WHEEL
conrun-0.1.3.dist-info/top_level.txt
conrun-0.1.3.dist-info/RECORD
