Metadata-Version: 2.4
Name: conrun
Version: 0.1.3
Summary: Simple concurrent runner for threads, processes, and async tasks
Author: Dmitrii Khudiakov
License: MIT
Project-URL: Homepage, https://github.com/DmitriiKhudiakov/conrun
Project-URL: Repository, https://github.com/DmitriiKhudiakov/conrun
Project-URL: Issues, https://github.com/DmitriiKhudiakov/conrun/issues
Project-URL: Changelog, https://github.com/DmitriiKhudiakov/conrun/releases
Keywords: concurrent,asyncio,parallel,threads,tasks
Classifier: Programming Language :: Python :: 3
Classifier: Programming Language :: Python :: 3.10
Classifier: Programming Language :: Python :: 3.11
Classifier: Programming Language :: Python :: 3.12
Classifier: Programming Language :: Python :: 3.13
Classifier: License :: OSI Approved :: MIT License
Classifier: Operating System :: OS Independent
Classifier: Topic :: Software Development :: Libraries
Classifier: Topic :: Utilities
Requires-Python: >=3.10
License-File: LICENSE
Dynamic: license-file
